LICENSE.txt
MANIFEST.in
README.rst
setup.py
fbu/Multichain.py
fbu/PyFBU.py
fbu/__init__.py
fbu/monitoring.py
fbu/potentials.py
fbu/priors.py
fbu/tests
fbu/tikhonov.py
fbu.egg-info/PKG-INFO
fbu.egg-info/SOURCES.txt
fbu.egg-info/dependency_links.txt
fbu.egg-info/requires.txt
fbu.egg-info/top_level.txt
fbu/tests/__init__.py
fbu/tests/test_basic.py