Metadata-Version: 1.0
Name: fbu
Version: 0.0.1
Summary: UNKNOWN
Home-page: https://github.com/gerbaudo/fbu
Author: Davide Gerbaudo, Clement Helsens and Francesco Rubbo
Author-email: rubbo.francesco@gmail.com
License: LICENSE.txt
Platform: UNKNOWN
Classifier: Development Status :: 3 - Alpha
Classifier: Intended Audience :: Science/Research
Classifier: License :: OSI Approved :: GNU General Public License v2 (GPLv2)
Classifier: Programming Language :: Python :: 2.7
Classifier: Topic :: Scientific/Engineering :: Physics
Classifier: Operating System :: OS Independent
